navconfig/__init__.py
navconfig/cli.py
navconfig/conf.py
navconfig/exceptions.c
navconfig/exceptions.cp310-win_amd64.pyd
navconfig/exceptions.pxd
navconfig/exceptions.pyx
navconfig/kardex.py
navconfig/logging.yaml
navconfig/project.py
navconfig/py.typed
navconfig/version.py
navconfig/contrib/__init__.py
navconfig/contrib/web.py
navconfig/cyphers/__init__.py
navconfig/cyphers/abstract.py
navconfig/cyphers/fernet.py
navconfig/loaders/__init__.py
navconfig/loaders/abstract.py
navconfig/loaders/crypt.py
navconfig/loaders/drive.py
navconfig/loaders/file.py
navconfig/loaders/pyproject.py
navconfig/loaders/toml.py
navconfig/loaders/vault.py
navconfig/loaders/yaml.py
navconfig/loaders/parsers/__init__.py
navconfig/loaders/parsers/toml.cp310-win_amd64.pyd
navconfig/loaders/parsers/toml.cpp
navconfig/loaders/parsers/toml.pyx
navconfig/loaders/parsers/yaml.cp310-win_amd64.pyd
navconfig/loaders/parsers/yaml.cpp
navconfig/loaders/parsers/yaml.pyx
navconfig/logging/__init__.py
navconfig/logging/formatter.py
navconfig/logging/logger.cp310-win_amd64.pyd
navconfig/logging/logger.cpp
navconfig/logging/logger.pyi
navconfig/logging/logger.pyx
navconfig/logging/handlers/__init__.py
navconfig/logging/handlers/abstract.py
navconfig/logging/handlers/file.py
navconfig/logging/handlers/logstash.py
navconfig/logging/handlers/mail.py
navconfig/readers/__init__.py
navconfig/readers/abstract.py
navconfig/readers/memcache.py
navconfig/readers/redis.py
navconfig/readers/vault.py
navconfig/utils/__init__.py
navconfig/utils/functions.cp310-win_amd64.pyd
navconfig/utils/functions.cpp
navconfig/utils/functions.pyx
navconfig/utils/json.cp310-win_amd64.pyd
navconfig/utils/json.cpp
navconfig/utils/json.pyx
navconfig/utils/settings.py
navconfig/utils/types.cp310-win_amd64.pyd
navconfig/utils/types.cpp
navconfig/utils/types.pyx
navconfig/utils/uvl.py
navconfig-2.0.1.dist-info/licenses/LICENSE
navconfig-2.0.1.dist-info/METADATA
navconfig-2.0.1.dist-info/WHEEL
navconfig-2.0.1.dist-info/entry_points.txt
navconfig-2.0.1.dist-info/top_level.txt
navconfig-2.0.1.dist-info/RECORD
