Metadata-Version: 2.4
Name: navconfig
Version: 2.0.1
Summary: Universal Configuration Management for Python Projects.
Author-email: Jesus Lara Gimenez <jesuslarag@gmail.com>
Maintainer-email: Jesus Lara <jesuslara@phenobarbital.info>
License: MIT
Project-URL: Homepage, https://github.com/phenobarbital/navconfig
Project-URL: Repository, https://github.com/phenobarbital/navconfig
Project-URL: Documentation, https://github.com/phenobarbital/navconfig
Project-URL: Bug Tracker, https://github.com/phenobarbital/navconfig/issues
Project-URL: Funding, https://paypal.me/phenobarbital
Project-URL: Say Thanks!, https://saythanks.io/to/phenobarbital
Keywords: aiohttp,settings,configuration,conf,configuration-management
Classifier: Development Status :: 4 - Beta
Classifier: Intended Audience :: Developers
Classifier: Intended Audience :: System Administrators
Classifier: Operating System :: OS Independent
Classifier: Programming Language :: Python :: 3.9
Classifier: Programming Language :: Python :: 3.10
Classifier: Programming Language :: Python :: 3.11
Classifier: Programming Language :: Python :: 3.12
Classifier: Programming Language :: Python
Classifier: Typing :: Typed
Classifier: Environment :: Web Environment
Classifier: Framework :: AsyncIO
Classifier: Topic :: Software Development :: Libraries :: Application Frameworks
Classifier: Topic :: Software Development :: Libraries :: Python Modules
Classifier: Topic :: Software Development :: Build Tools
Classifier: License :: OSI Approved :: MIT License
Requires-Python: >=3.10.1
License-File: LICENSE
Requires-Dist: Cython>=3.0.11
Requires-Dist: asyncio>=3.4.3
Requires-Dist: python-dotenv>=1.0.1
Requires-Dist: configparser>=6.0.0
Requires-Dist: python-dateutil>=2.8.2
Requires-Dist: objectpath>=0.6.1
Requires-Dist: iso8601>=2.1.0
Requires-Dist: pycparser>=2.21
Requires-Dist: orjson>=3.10.3
Requires-Dist: pycryptodomex>=3.20.0
Requires-Dist: cryptography>=43.0.1
Requires-Dist: aiofiles<=24.1.0,>=23.2.1
Requires-Dist: jsonpickle<=3.0.2,>=1.2
Requires-Dist: pytomlpp>=1.0.13
Requires-Dist: PyYAML>=6.0
Requires-Dist: requests>=2.32.4
Requires-Dist: hvac==2.3.0
Provides-Extra: uvloop
Requires-Dist: uvloop>=0.21.0; extra == "uvloop"
Provides-Extra: memcache
Requires-Dist: pylibmc>=1.6.3; extra == "memcache"
Requires-Dist: aiomcache>=0.8.2; extra == "memcache"
Provides-Extra: gdrive
Requires-Dist: PyDrive>=1.3.1; extra == "gdrive"
Provides-Extra: logstash
Requires-Dist: python-logstash-async<=3.0.0,>=2.7.2; extra == "logstash"
Provides-Extra: redis
Requires-Dist: redis<=5.2.1,>=5.0.8; extra == "redis"
Provides-Extra: hvac
Requires-Dist: hvac>=2.3.0; extra == "hvac"
Provides-Extra: build
Requires-Dist: setuptools>=74.0.0; extra == "build"
Requires-Dist: Cython>=3.0.11; extra == "build"
Requires-Dist: wheel>=0.44.0; extra == "build"
Provides-Extra: dev
Requires-Dist: pytest>=7.0.0; extra == "dev"
Requires-Dist: pytest-cov>=4.0.0; extra == "dev"
Requires-Dist: pytest-asyncio>=0.21.0; extra == "dev"
Requires-Dist: ruff>=0.1.0; extra == "dev"
Requires-Dist: black>=23.0.0; extra == "dev"
Requires-Dist: mypy>=1.0.0; extra == "dev"
Requires-Dist: pre-commit>=3.0.0; extra == "dev"
Provides-Extra: default
Requires-Dist: pytomlpp>=1.0.13; extra == "default"
Requires-Dist: redis<=5.2.1,>=5.0.8; extra == "default"
Requires-Dist: python-logstash-async>=2.7.2; extra == "default"
Requires-Dist: PyYAML>=6.0; extra == "default"
Requires-Dist: hvac>=2.3.0; extra == "default"
Provides-Extra: all
Requires-Dist: pytomlpp>=1.0.13; extra == "all"
Requires-Dist: redis<=5.2.1,>=5.0.8; extra == "all"
Requires-Dist: python-logstash-async>=2.7.2; extra == "all"
Requires-Dist: PyYAML>=6.0; extra == "all"
Requires-Dist: aiomcache>=0.8.2; extra == "all"
Requires-Dist: hvac>=2.3.0; extra == "all"
Requires-Dist: uvloop>=0.21.0; extra == "all"
Dynamic: license-file
